{
  "gameId": 1685,
  "showNumber": 1326,
  "airDate": "May 14, 1990",
  "season": null,
  "isSpecial": false,
  "tournamentType": null,
  "categories": [
    {
      "name": "WORD ORIGINS",
      "round": "single",
      "position": 0,
      "clues": [
        {
          "question": "This name for an earthenware beer mug is German for \"stone\"",
          "answer": "Stein",
          "value": 100,
          "dailyDouble": false,
          "tripleStumper": false,
          "isFinalJeopardy": false,
          "category": "WORD ORIGINS",
          "round": "single",
          "rowIndex": 0,
          "clueId": "g1685-s-c0-r0"
        },
        {
          "question": "Italian for \"first lady\", it can refer to a temperamental woman or man",
          "answer": "Prima donna",
          "value": 200,
          "dailyDouble": false,
          "tripleStumper": false,
          "isFinalJeopardy": false,
          "category": "WORD ORIGINS",
          "round": "single",
          "rowIndex": 1,
          "clueId": "g1685-s-c0-r1"
        },
        {
          "question": "From the Latin for \"worm\", it's defined simply as \"animals obnoxious to man\"",
          "answer": "Vermin",
          "value": 300,
          "dailyDouble": false,
          "tripleStumper": false,
          "isFinalJeopardy": false,
          "category": "WORD ORIGINS",
          "round": "single",
          "rowIndex": 2,
          "clueId": "g1685-s-c0-r2"
        },
        {
          "question": "From the Latin for \"hunger\", it's a period when food is extremely scarce",
          "answer": "Famine",
          "value": 400,
          "dailyDouble": false,
          "tripleStumper": false,
          "isFinalJeopardy": false,
          "category": "WORD ORIGINS",
          "round": "single",
          "rowIndex": 3,
          "clueId": "g1685-s-c0-r3"
        },
        {
          "question": "This Scottish cap was named for the hero of a Robert Burns poem",
          "answer": "Tam O' Shanter",
          "value": 500,
          "dailyDouble": false,
          "tripleStumper": false,
          "isFinalJeopardy": false,
          "category": "WORD ORIGINS",
          "round": "single",
          "rowIndex": 4,
          "clueId": "g1685-s-c0-r4"
        }
      ]
    },
    {
      "name": "COMIC BOOKS",
      "round": "single",
      "position": 1,
      "clues": [
        {
          "question": "In addition to toys & a cartoon series, this comedy cop school series has spawned a Marvel comic",
          "answer": "Police Academy",
          "value": 100,
          "dailyDouble": false,
          "tripleStumper": false,
          "isFinalJeopardy": false,
          "category": "COMIC BOOKS",
          "round": "single",
          "rowIndex": 0,
          "clueId": "g1685-s-c1-r0"
        },
        {
          "question": "After DC killed off Jason Todd, Tim Drake was written in to become this red-breasted hero",
          "answer": "Robin",
          "value": 200,
          "dailyDouble": false,
          "tripleStumper": false,
          "isFinalJeopardy": false,
          "category": "COMIC BOOKS",
          "round": "single",
          "rowIndex": 1,
          "clueId": "g1685-s-c1-r1"
        },
        {
          "question": "Getting caught in a gamma bomb blast in 1989 turned him from green to gray & boosted his intelligence",
          "answer": "The Hulk",
          "value": 300,
          "dailyDouble": false,
          "tripleStumper": false,
          "isFinalJeopardy": false,
          "category": "COMIC BOOKS",
          "round": "single",
          "rowIndex": 2,
          "clueId": "g1685-s-c1-r2"
        },
        {
          "question": "Crimefighting team seen here in their new incarnations for the 1990s:",
          "answer": "The Green Hornet & Kato",
          "value": 1300,
          "dailyDouble": true,
          "tripleStumper": true,
          "isFinalJeopardy": false,
          "category": "COMIC BOOKS",
          "round": "single",
          "rowIndex": 3,
          "clueId": "g1685-s-c1-r3"
        },
        {
          "question": "Fictional detective with his own mystery magazine, he recently guest sleuthed with the Maze Agency",
          "answer": "Ellery Queen",
          "value": 500,
          "dailyDouble": false,
          "tripleStumper": false,
          "isFinalJeopardy": false,
          "category": "COMIC BOOKS",
          "round": "single",
          "rowIndex": 4,
          "clueId": "g1685-s-c1-r4"
        }
      ]
    },
    {
      "name": "ECONOMICS",
      "round": "single",
      "position": 2,
      "clues": [
        {
          "question": "Economists say if the rate of this is 2 or 3% a year, it's normal; if it's \"galloping\", it's bad",
          "answer": "Inflation",
          "value": 100,
          "dailyDouble": false,
          "tripleStumper": false,
          "isFinalJeopardy": false,
          "category": "ECONOMICS",
          "round": "single",
          "rowIndex": 0,
          "clueId": "g1685-s-c2-r0"
        },
        {
          "question": "After deducting all expenses from your gross profit, you're left with this",
          "answer": "Net",
          "value": 200,
          "dailyDouble": false,
          "tripleStumper": false,
          "isFinalJeopardy": false,
          "category": "ECONOMICS",
          "round": "single",
          "rowIndex": 1,
          "clueId": "g1685-s-c2-r1"
        },
        {
          "question": "Holders of this type of stock take precedence over common stock holders",
          "answer": "Preferred",
          "value": 300,
          "dailyDouble": false,
          "tripleStumper": false,
          "isFinalJeopardy": false,
          "category": "ECONOMICS",
          "round": "single",
          "rowIndex": 2,
          "clueId": "g1685-s-c2-r2"
        },
        {
          "question": "This system is a direct exchange of goods or services without the use of money",
          "answer": "Barter",
          "value": 400,
          "dailyDouble": false,
          "tripleStumper": false,
          "isFinalJeopardy": false,
          "category": "ECONOMICS",
          "round": "single",
          "rowIndex": 3,
          "clueId": "g1685-s-c2-r3"
        },
        {
          "question": "First American to win the Nobel Prize in Economics, he's the author of a widely used college textbook",
          "answer": "Paul Samuelson",
          "value": 500,
          "dailyDouble": false,
          "tripleStumper": true,
          "isFinalJeopardy": false,
          "category": "ECONOMICS",
          "round": "single",
          "rowIndex": 4,
          "clueId": "g1685-s-c2-r4"
        }
      ]
    },
    {
      "name": "HOLIDAYS & OBSERVANCES",
      "round": "single",
      "position": 3,
      "clues": [
        {
          "question": "The most candy bought for a holiday is for this springtime one, not Valentine's Day",
          "answer": "Easter",
          "value": 100,
          "dailyDouble": false,
          "tripleStumper": false,
          "isFinalJeopardy": false,
          "category": "HOLIDAYS & OBSERVANCES",
          "round": "single",
          "rowIndex": 0,
          "clueId": "g1685-s-c3-r0"
        },
        {
          "question": "The New Year's Day of this calendar can fall between our January 20 & February 20",
          "answer": "Chinese calendar",
          "value": 200,
          "dailyDouble": false,
          "tripleStumper": false,
          "isFinalJeopardy": false,
          "category": "HOLIDAYS & OBSERVANCES",
          "round": "single",
          "rowIndex": 1,
          "clueId": "g1685-s-c3-r1"
        },
        {
          "question": "Bennington Battle Day, August 16th, is a legal holiday in this New England state",
          "answer": "Vermont",
          "value": 300,
          "dailyDouble": false,
          "tripleStumper": false,
          "isFinalJeopardy": false,
          "category": "HOLIDAYS & OBSERVANCES",
          "round": "single",
          "rowIndex": 2,
          "clueId": "g1685-s-c3-r2"
        },
        {
          "question": "The red or white rose is the official flower of this Sunday observance in June",
          "answer": "Father's Day",
          "value": 400,
          "dailyDouble": false,
          "tripleStumper": false,
          "isFinalJeopardy": false,
          "category": "HOLIDAYS & OBSERVANCES",
          "round": "single",
          "rowIndex": 3,
          "clueId": "g1685-s-c3-r3"
        },
        {
          "question": "Flag Day is a legal holiday only in this state where Betsy Ross worked as a seamstress",
          "answer": "Pennsylvania",
          "value": 500,
          "dailyDouble": false,
          "tripleStumper": false,
          "isFinalJeopardy": false,
          "category": "HOLIDAYS & OBSERVANCES",
          "round": "single",
          "rowIndex": 4,
          "clueId": "g1685-s-c3-r4"
        }
      ]
    },
    {
      "name": "U.S. GEOGRAPHY",
      "round": "single",
      "position": 4,
      "clues": [
        {
          "question": "This river that rises at Lake Itasca drains about 1/8 of the North American continent",
          "answer": "Mississippi River",
          "value": 100,
          "dailyDouble": false,
          "tripleStumper": false,
          "isFinalJeopardy": false,
          "category": "U.S. GEOGRAPHY",
          "round": "single",
          "rowIndex": 0,
          "clueId": "g1685-s-c4-r0"
        },
        {
          "question": "Of New York City's 5 boroughs, the one that is New York County",
          "answer": "Manhattan",
          "value": 200,
          "dailyDouble": false,
          "tripleStumper": false,
          "isFinalJeopardy": false,
          "category": "U.S. GEOGRAPHY",
          "round": "single",
          "rowIndex": 1,
          "clueId": "g1685-s-c4-r1"
        },
        {
          "question": "This lake was created when Hoover Dam was built on the Colorado River",
          "answer": "Lake Mead",
          "value": 300,
          "dailyDouble": false,
          "tripleStumper": false,
          "isFinalJeopardy": false,
          "category": "U.S. GEOGRAPHY",
          "round": "single",
          "rowIndex": 2,
          "clueId": "g1685-s-c4-r2"
        },
        {
          "question": "In Kansas more people live in this city than in Topeka & Kansas City combined",
          "answer": "Wichita",
          "value": 400,
          "dailyDouble": false,
          "tripleStumper": false,
          "isFinalJeopardy": false,
          "category": "U.S. GEOGRAPHY",
          "round": "single",
          "rowIndex": 3,
          "clueId": "g1685-s-c4-r3"
        },
        {
          "question": "The 1842 Webster-Ashburton Treaty fixed this state's border with New Brunswick",
          "answer": "Maine",
          "value": 500,
          "dailyDouble": false,
          "tripleStumper": false,
          "isFinalJeopardy": false,
          "category": "U.S. GEOGRAPHY",
          "round": "single",
          "rowIndex": 4,
          "clueId": "g1685-s-c4-r4"
        }
      ]
    },
    {
      "name": "ACCORDING TO PEOPLE",
      "round": "single",
      "position": 5,
      "clues": [
        {
          "question": "When Pat Sajak got married, People quoted her as saying, \"Th*y'll l*v* happ*ly *v*r aft*r!\"",
          "answer": "Vanna White",
          "value": 100,
          "dailyDouble": false,
          "tripleStumper": false,
          "isFinalJeopardy": false,
          "category": "ACCORDING TO PEOPLE",
          "round": "single",
          "rowIndex": 0,
          "clueId": "g1685-s-c5-r0"
        },
        {
          "question": "People said this late star's \"slapstick made her the greatest comedienne of all time.\"",
          "answer": "Lucille Ball",
          "value": 200,
          "dailyDouble": false,
          "tripleStumper": false,
          "isFinalJeopardy": false,
          "category": "ACCORDING TO PEOPLE",
          "round": "single",
          "rowIndex": 1,
          "clueId": "g1685-s-c5-r1"
        },
        {
          "question": "People said that Helen Gurley Brown wants Johnny Depp to pose nude for this magazine",
          "answer": "Cosmopolitan",
          "value": 300,
          "dailyDouble": false,
          "tripleStumper": false,
          "isFinalJeopardy": false,
          "category": "ACCORDING TO PEOPLE",
          "round": "single",
          "rowIndex": 2,
          "clueId": "g1685-s-c5-r2"
        },
        {
          "question": "Naming him \"The Sexiest Man Alive (1989)\", People called him \"Older, balder...and better!\"",
          "answer": "Sean Connery",
          "value": 400,
          "dailyDouble": false,
          "tripleStumper": false,
          "isFinalJeopardy": false,
          "category": "ACCORDING TO PEOPLE",
          "round": "single",
          "rowIndex": 3,
          "clueId": "g1685-s-c5-r3"
        },
        {
          "question": "1 of \"The 25 Most Intriguing People\" of 1989, she celebrated her 31st birthday with Warren Beatty",
          "answer": "Madonna",
          "value": 500,
          "dailyDouble": false,
          "tripleStumper": false,
          "isFinalJeopardy": false,
          "category": "ACCORDING TO PEOPLE",
          "round": "single",
          "rowIndex": 4,
          "clueId": "g1685-s-c5-r4"
        }
      ]
    },
    {
      "name": "FICTIONAL CHARACTERS",
      "round": "double",
      "position": 0,
      "clues": [
        {
          "question": "This captain of the Nautilus, whose name means \"no one\", disappears at the end of the novel",
          "answer": "Captain Nemo",
          "value": 200,
          "dailyDouble": false,
          "tripleStumper": false,
          "isFinalJeopardy": false,
          "category": "FICTIONAL CHARACTERS",
          "round": "double",
          "rowIndex": 0,
          "clueId": "g1685-d-c0-r0"
        },
        {
          "question": "John is a Shakespeare-quoting \"savage\" found on a N.M. reservation in this Huxley novel",
          "answer": "\"Brave New World\"",
          "value": 400,
          "dailyDouble": false,
          "tripleStumper": false,
          "isFinalJeopardy": false,
          "category": "FICTIONAL CHARACTERS",
          "round": "double",
          "rowIndex": 1,
          "clueId": "g1685-d-c0-r1"
        },
        {
          "question": "In wooing her, Siegfried was standing in for someone else, & when she found out, she killed him",
          "answer": "Brunhilde",
          "value": 600,
          "dailyDouble": false,
          "tripleStumper": false,
          "isFinalJeopardy": false,
          "category": "FICTIONAL CHARACTERS",
          "round": "double",
          "rowIndex": 2,
          "clueId": "g1685-d-c0-r2"
        },
        {
          "question": "The silly Mrs. Bennet is the mother of Elizabeth, Jane, Lydia, Kitty & Mary in this classic",
          "answer": "\"Pride And Prejudice\"",
          "value": 1200,
          "dailyDouble": true,
          "tripleStumper": false,
          "isFinalJeopardy": false,
          "category": "FICTIONAL CHARACTERS",
          "round": "double",
          "rowIndex": 3,
          "clueId": "g1685-d-c0-r3"
        },
        {
          "question": "Cecilia Brady is out to kill her father in this last F. Scott Fitzgerald novel",
          "answer": "\"The Last Tycoon\"",
          "value": 1000,
          "dailyDouble": false,
          "tripleStumper": false,
          "isFinalJeopardy": false,
          "category": "FICTIONAL CHARACTERS",
          "round": "double",
          "rowIndex": 4,
          "clueId": "g1685-d-c0-r4"
        }
      ]
    },
    {
      "name": "EUROPEAN HISTORY",
      "round": "double",
      "position": 1,
      "clues": [
        {
          "question": "He didn't lead the march on Rome in 1922; he waited in Milan until he got the \"all clear\" & then went",
          "answer": "Benito Mussolini",
          "value": 200,
          "dailyDouble": false,
          "tripleStumper": false,
          "isFinalJeopardy": false,
          "category": "EUROPEAN HISTORY",
          "round": "double",
          "rowIndex": 0,
          "clueId": "g1685-d-c1-r0"
        },
        {
          "question": "Noted for saying \"I am the state,\" he ruled France for 72 years, 1643-1715",
          "answer": "Louis XIV",
          "value": 400,
          "dailyDouble": false,
          "tripleStumper": false,
          "isFinalJeopardy": false,
          "category": "EUROPEAN HISTORY",
          "round": "double",
          "rowIndex": 1,
          "clueId": "g1685-d-c1-r1"
        },
        {
          "question": "Romania was one Warsaw Pact country that didn't participate in the 1968 invasion of this country",
          "answer": "Czechoslovakia",
          "value": 600,
          "dailyDouble": false,
          "tripleStumper": false,
          "isFinalJeopardy": false,
          "category": "EUROPEAN HISTORY",
          "round": "double",
          "rowIndex": 2,
          "clueId": "g1685-d-c1-r2"
        },
        {
          "question": "He became king of Spain in 1975 after Franco's death",
          "answer": "Juan Carlos I",
          "value": 800,
          "dailyDouble": false,
          "tripleStumper": false,
          "isFinalJeopardy": false,
          "category": "EUROPEAN HISTORY",
          "round": "double",
          "rowIndex": 3,
          "clueId": "g1685-d-c1-r3"
        },
        {
          "question": "In 1924 U.S. banker Charles Dawes came up with a plan to help this country pay its war reparations",
          "answer": "Germany",
          "value": 1000,
          "dailyDouble": false,
          "tripleStumper": false,
          "isFinalJeopardy": false,
          "category": "EUROPEAN HISTORY",
          "round": "double",
          "rowIndex": 4,
          "clueId": "g1685-d-c1-r4"
        }
      ]
    },
    {
      "name": "COLLEGES & UNIVERSITIES",
      "round": "double",
      "position": 2,
      "clues": [
        {
          "question": "Transylvania U., the oldest university west of the Alleghenies, is in Lexington in this state",
          "answer": "Kentucky",
          "value": 200,
          "dailyDouble": false,
          "tripleStumper": false,
          "isFinalJeopardy": false,
          "category": "COLLEGES & UNIVERSITIES",
          "round": "double",
          "rowIndex": 0,
          "clueId": "g1685-d-c2-r0"
        },
        {
          "question": "A white oak at this New Brunswick, N.J. school supposedly inspired J. Kilmer to write \"Trees\"",
          "answer": "Rutgers",
          "value": 400,
          "dailyDouble": false,
          "tripleStumper": false,
          "isFinalJeopardy": false,
          "category": "COLLEGES & UNIVERSITIES",
          "round": "double",
          "rowIndex": 1,
          "clueId": "g1685-d-c2-r1"
        },
        {
          "question": "This school color of Syracuse gives its teams their nickname",
          "answer": "Orange (Orangemen)",
          "value": 600,
          "dailyDouble": false,
          "tripleStumper": false,
          "isFinalJeopardy": false,
          "category": "COLLEGES & UNIVERSITIES",
          "round": "double",
          "rowIndex": 2,
          "clueId": "g1685-d-c2-r2"
        },
        {
          "question": "This Ivy League school has 2 major art museums: the Fogg & the Sackler",
          "answer": "Harvard",
          "value": 800,
          "dailyDouble": false,
          "tripleStumper": false,
          "isFinalJeopardy": false,
          "category": "COLLEGES & UNIVERSITIES",
          "round": "double",
          "rowIndex": 3,
          "clueId": "g1685-d-c2-r3"
        },
        {
          "question": "One of the many institutions of higher learning in this state capital is Oglethorpe University",
          "answer": "Atlanta",
          "value": 1000,
          "dailyDouble": false,
          "tripleStumper": false,
          "isFinalJeopardy": false,
          "category": "COLLEGES & UNIVERSITIES",
          "round": "double",
          "rowIndex": 4,
          "clueId": "g1685-d-c2-r4"
        }
      ]
    },
    {
      "name": "QUOTES",
      "round": "double",
      "position": 3,
      "clues": [
        {
          "question": "According to Jonathan Swift, these \"and piecrust are made to be broken.\"",
          "answer": "Promises",
          "value": 200,
          "dailyDouble": false,
          "tripleStumper": false,
          "isFinalJeopardy": false,
          "category": "QUOTES",
          "round": "double",
          "rowIndex": 0,
          "clueId": "g1685-d-c3-r0"
        },
        {
          "question": "H.L. Mencken defined it as \"The inner voice which warns us that someone may be looking\"",
          "answer": "Conscience",
          "value": 400,
          "dailyDouble": false,
          "tripleStumper": false,
          "isFinalJeopardy": false,
          "category": "QUOTES",
          "round": "double",
          "rowIndex": 1,
          "clueId": "g1685-d-c3-r1"
        },
        {
          "question": "\"Love & Death\" director who said, \"It's not that I'm afraid to die; I just don't want to be there when it happens.\"",
          "answer": "Woody Allen",
          "value": 600,
          "dailyDouble": false,
          "tripleStumper": false,
          "isFinalJeopardy": false,
          "category": "QUOTES",
          "round": "double",
          "rowIndex": 2,
          "clueId": "g1685-d-c3-r2"
        },
        {
          "question": "This, said Wm. L. Garrison, \"will not be overthrown without...a most tremendous excitement.\"",
          "answer": "Slavery",
          "value": 800,
          "dailyDouble": false,
          "tripleStumper": false,
          "isFinalJeopardy": false,
          "category": "QUOTES",
          "round": "double",
          "rowIndex": 3,
          "clueId": "g1685-d-c3-r3"
        },
        {
          "question": "A biographer claimed he said, \"I disapprove of what you say, but I will defend to the death your right to say it.\"",
          "answer": "Voltaire",
          "value": 1000,
          "dailyDouble": false,
          "tripleStumper": false,
          "isFinalJeopardy": false,
          "category": "QUOTES",
          "round": "double",
          "rowIndex": 4,
          "clueId": "g1685-d-c3-r4"
        }
      ]
    },
    {
      "name": "BIOLOGY",
      "round": "double",
      "position": 4,
      "clues": [
        {
          "question": "Of all mammals, this one takes longest to mature",
          "answer": "Man (humans)",
          "value": 200,
          "dailyDouble": false,
          "tripleStumper": false,
          "isFinalJeopardy": false,
          "category": "BIOLOGY",
          "round": "double",
          "rowIndex": 0,
          "clueId": "g1685-d-c4-r0"
        },
        {
          "question": "The human body's largest bone",
          "answer": "Femur",
          "value": 400,
          "dailyDouble": false,
          "tripleStumper": false,
          "isFinalJeopardy": false,
          "category": "BIOLOGY",
          "round": "double",
          "rowIndex": 1,
          "clueId": "g1685-d-c4-r1"
        },
        {
          "question": "In 1956 scientists determined a normal human cell has this many chromosomes",
          "answer": "46",
          "value": 1000,
          "dailyDouble": true,
          "tripleStumper": false,
          "isFinalJeopardy": false,
          "category": "BIOLOGY",
          "round": "double",
          "rowIndex": 2,
          "clueId": "g1685-d-c4-r2"
        },
        {
          "question": "Light-sensitive layer of nerve tissue covering the back 2/3 of the eyeball, it's an extension of the brain",
          "answer": "Retina",
          "value": 800,
          "dailyDouble": false,
          "tripleStumper": false,
          "isFinalJeopardy": false,
          "category": "BIOLOGY",
          "round": "double",
          "rowIndex": 3,
          "clueId": "g1685-d-c4-r3"
        },
        {
          "question": "This Swedish botanist, known for his system of classification, was the first to note that whales are mammals",
          "answer": "Carl Linnaeus",
          "value": 1000,
          "dailyDouble": false,
          "tripleStumper": false,
          "isFinalJeopardy": false,
          "category": "BIOLOGY",
          "round": "double",
          "rowIndex": 4,
          "clueId": "g1685-d-c4-r4"
        }
      ]
    },
    {
      "name": "MUSICAL INSTRUMENTS",
      "round": "double",
      "position": 5,
      "clues": [
        {
          "question": "In the '30s Laurens Hammond patented the 1st commercially practical electronic one of these",
          "answer": "Organ",
          "value": 200,
          "dailyDouble": false,
          "tripleStumper": false,
          "isFinalJeopardy": false,
          "category": "MUSICAL INSTRUMENTS",
          "round": "double",
          "rowIndex": 0,
          "clueId": "g1685-d-c5-r0"
        },
        {
          "question": "The Highland version of this instrument has a blowpipe, a chanter & 3 drones",
          "answer": "Bagpipes",
          "value": 400,
          "dailyDouble": false,
          "tripleStumper": false,
          "isFinalJeopardy": false,
          "category": "MUSICAL INSTRUMENTS",
          "round": "double",
          "rowIndex": 1,
          "clueId": "g1685-d-c5-r1"
        },
        {
          "question": "In 1709 inventor B. Cristofori gave this instrument a name meaning \"harpsichord with soft & loud\"",
          "answer": "Piano",
          "value": 600,
          "dailyDouble": false,
          "tripleStumper": false,
          "isFinalJeopardy": false,
          "category": "MUSICAL INSTRUMENTS",
          "round": "double",
          "rowIndex": 2,
          "clueId": "g1685-d-c5-r2"
        },
        {
          "question": "Also called a helicon, this 3-valve tuba wraps around the player's body & has a flaring bell",
          "answer": "Sousaphone",
          "value": 800,
          "dailyDouble": false,
          "tripleStumper": false,
          "isFinalJeopardy": false,
          "category": "MUSICAL INSTRUMENTS",
          "round": "double",
          "rowIndex": 3,
          "clueId": "g1685-d-c5-r3"
        },
        {
          "question": "2 types of this Italian plucked stringed instrument are the Neopolitan & the rarer Milanese",
          "answer": "Mandolin",
          "value": 1000,
          "dailyDouble": false,
          "tripleStumper": false,
          "isFinalJeopardy": false,
          "category": "MUSICAL INSTRUMENTS",
          "round": "double",
          "rowIndex": 4,
          "clueId": "g1685-d-c5-r4"
        }
      ]
    },
    {
      "name": "THE BIBLE",
      "round": "final",
      "position": 0,
      "clues": [
        {
          "question": "Of the men mentioned in the King James Version, he's first alphabetically",
          "answer": "Aaron (Moses' brother)",
          "value": null,
          "dailyDouble": false,
          "tripleStumper": false,
          "isFinalJeopardy": true,
          "category": "THE BIBLE",
          "round": "final",
          "rowIndex": 0,
          "clueId": "g1685-f-c0-r0"
        }
      ]
    }
  ]
}