{
  "gameId": 7735,
  "showNumber": 30,
  "airDate": "October 19, 1984",
  "season": null,
  "isSpecial": false,
  "tournamentType": null,
  "categories": [
    {
      "name": "POP MUSIC",
      "round": "single",
      "position": 0,
      "clues": [
        {
          "question": "Michael Jackson keeps the beat with this Beatle in \"The Girl Is Mine\" and \"Say, Say, Say\"",
          "answer": "Paul McCartney",
          "value": 100,
          "dailyDouble": false,
          "tripleStumper": false,
          "isFinalJeopardy": false,
          "category": "POP MUSIC",
          "round": "single",
          "rowIndex": 0,
          "clueId": "g7735-s-c0-r0"
        },
        {
          "question": "Actress whose \"eyes\" are focused on in Kim Carnes' hit",
          "answer": "Bette Davis",
          "value": 200,
          "dailyDouble": false,
          "tripleStumper": false,
          "isFinalJeopardy": false,
          "category": "POP MUSIC",
          "round": "single",
          "rowIndex": 1,
          "clueId": "g7735-s-c0-r1"
        },
        {
          "question": "This Grammy-winning group shares its name with Dorothy's dog",
          "answer": "Toto",
          "value": 300,
          "dailyDouble": false,
          "tripleStumper": false,
          "isFinalJeopardy": false,
          "category": "POP MUSIC",
          "round": "single",
          "rowIndex": 2,
          "clueId": "g7735-s-c0-r2"
        },
        {
          "question": "Hotel that the Eagles \"welcomed\" us to in the '77 hit",
          "answer": "Hotel California",
          "value": 400,
          "dailyDouble": false,
          "tripleStumper": false,
          "isFinalJeopardy": false,
          "category": "POP MUSIC",
          "round": "single",
          "rowIndex": 3,
          "clueId": "g7735-s-c0-r3"
        },
        {
          "question": "Old standards bandleader who arranged Linda Ronstadt's \"What's New\" album",
          "answer": "Nelson Riddle",
          "value": 500,
          "dailyDouble": false,
          "tripleStumper": false,
          "isFinalJeopardy": false,
          "category": "POP MUSIC",
          "round": "single",
          "rowIndex": 4,
          "clueId": "g7735-s-c0-r4"
        }
      ]
    },
    {
      "name": "BRITISH ROYALTY",
      "round": "single",
      "position": 1,
      "clues": [
        {
          "question": "Title for husband of a reigning queen; Prince Philip is one",
          "answer": "a consort",
          "value": 100,
          "dailyDouble": false,
          "tripleStumper": false,
          "isFinalJeopardy": false,
          "category": "BRITISH ROYALTY",
          "round": "single",
          "rowIndex": 0,
          "clueId": "g7735-s-c1-r0"
        },
        {
          "question": "Law of primogeniture ensures inheritance & throne to this family member",
          "answer": "the first son",
          "value": 200,
          "dailyDouble": false,
          "tripleStumper": false,
          "isFinalJeopardy": false,
          "category": "BRITISH ROYALTY",
          "round": "single",
          "rowIndex": 1,
          "clueId": "g7735-s-c1-r1"
        },
        {
          "question": "Title given to first male heir to the throne of Great Britain",
          "answer": "the Prince of Wales",
          "value": 300,
          "dailyDouble": false,
          "tripleStumper": false,
          "isFinalJeopardy": false,
          "category": "BRITISH ROYALTY",
          "round": "single",
          "rowIndex": 2,
          "clueId": "g7735-s-c1-r2"
        },
        {
          "question": "British heads get this on the Stone of Scone",
          "answer": "their coronation (crowned)",
          "value": 400,
          "dailyDouble": false,
          "tripleStumper": false,
          "isFinalJeopardy": false,
          "category": "BRITISH ROYALTY",
          "round": "single",
          "rowIndex": 3,
          "clueId": "g7735-s-c1-r3"
        },
        {
          "question": "The execution of Charles I was 1st blow to this doctrine that only God could punish kings",
          "answer": "the divine right of kings",
          "value": 500,
          "dailyDouble": false,
          "tripleStumper": true,
          "isFinalJeopardy": false,
          "category": "BRITISH ROYALTY",
          "round": "single",
          "rowIndex": 4,
          "clueId": "g7735-s-c1-r4"
        }
      ]
    },
    {
      "name": "RELIGION",
      "round": "single",
      "position": 2,
      "clues": [
        {
          "question": "Mary Baker Eddy called it \"a scientific approach to healing\"",
          "answer": "Christian Science",
          "value": 100,
          "dailyDouble": false,
          "tripleStumper": false,
          "isFinalJeopardy": false,
          "category": "RELIGION",
          "round": "single",
          "rowIndex": 0,
          "clueId": "g7735-s-c2-r0"
        }
      ]
    },
    {
      "name": "RULES OF THE GAME",
      "round": "single",
      "position": 3,
      "clues": [
        {
          "question": "Hit a ball through wickets to touch a peg",
          "answer": "croquet",
          "value": 100,
          "dailyDouble": false,
          "tripleStumper": false,
          "isFinalJeopardy": false,
          "category": "RULES OF THE GAME",
          "round": "single",
          "rowIndex": 0,
          "clueId": "g7735-s-c3-r0"
        },
        {
          "question": "In poker, it beats 3 of a kind, but not a flush",
          "answer": "a straight",
          "value": 200,
          "dailyDouble": false,
          "tripleStumper": false,
          "isFinalJeopardy": false,
          "category": "RULES OF THE GAME",
          "round": "single",
          "rowIndex": 1,
          "clueId": "g7735-s-c3-r1"
        },
        {
          "question": "A team of nurses in Dublin draw the names of the horses & winners in it",
          "answer": "the Irish (Hospital) Sweepstakes",
          "value": 300,
          "dailyDouble": false,
          "tripleStumper": false,
          "isFinalJeopardy": false,
          "category": "RULES OF THE GAME",
          "round": "single",
          "rowIndex": 2,
          "clueId": "g7735-s-c3-r2"
        },
        {
          "question": "Propel 300 lb. opponent out of circle or have him touch ground with other than his feet",
          "answer": "sumo wrestling",
          "value": 400,
          "dailyDouble": false,
          "tripleStumper": false,
          "isFinalJeopardy": false,
          "category": "RULES OF THE GAME",
          "round": "single",
          "rowIndex": 3,
          "clueId": "g7735-s-c3-r3"
        },
        {
          "question": "A blot when hit must be put on the bar in this game",
          "answer": "backgammon",
          "value": 500,
          "dailyDouble": false,
          "tripleStumper": false,
          "isFinalJeopardy": false,
          "category": "RULES OF THE GAME",
          "round": "single",
          "rowIndex": 4,
          "clueId": "g7735-s-c3-r4"
        }
      ]
    },
    {
      "name": "INTERNATIONAL FOODS",
      "round": "single",
      "position": 4,
      "clues": [
        {
          "question": "A hole-y cheese from Alpine heights",
          "answer": "Swiss cheese",
          "value": 100,
          "dailyDouble": false,
          "tripleStumper": false,
          "isFinalJeopardy": false,
          "category": "INTERNATIONAL FOODS",
          "round": "single",
          "rowIndex": 0,
          "clueId": "g7735-s-c4-r0"
        },
        {
          "question": "Hybrid mandarin orange named for Moroccan seaport",
          "answer": "a tangerine",
          "value": 200,
          "dailyDouble": false,
          "tripleStumper": false,
          "isFinalJeopardy": false,
          "category": "INTERNATIONAL FOODS",
          "round": "single",
          "rowIndex": 1,
          "clueId": "g7735-s-c4-r1"
        },
        {
          "question": "Succulent sauce named for Netherlands",
          "answer": "Hollandaise sauce",
          "value": 300,
          "dailyDouble": false,
          "tripleStumper": true,
          "isFinalJeopardy": false,
          "category": "INTERNATIONAL FOODS",
          "round": "single",
          "rowIndex": 2,
          "clueId": "g7735-s-c4-r2"
        },
        {
          "question": "Salad named for restaurant owner in Tijuana, Mexico, not for the Roman emperor",
          "answer": "Caesar salad",
          "value": 400,
          "dailyDouble": false,
          "tripleStumper": false,
          "isFinalJeopardy": false,
          "category": "INTERNATIONAL FOODS",
          "round": "single",
          "rowIndex": 3,
          "clueId": "g7735-s-c4-r3"
        },
        {
          "question": "Smoked liver sausage named for region of Brunswick in Germany",
          "answer": "Braunschweiger",
          "value": 500,
          "dailyDouble": false,
          "tripleStumper": false,
          "isFinalJeopardy": false,
          "category": "INTERNATIONAL FOODS",
          "round": "single",
          "rowIndex": 4,
          "clueId": "g7735-s-c4-r4"
        }
      ]
    },
    {
      "name": "WEATHER",
      "round": "single",
      "position": 5,
      "clues": [
        {
          "question": "Cocky rooftop device that gives us \"NEWS\" about the wind",
          "answer": "a weather vane",
          "value": 100,
          "dailyDouble": false,
          "tripleStumper": false,
          "isFinalJeopardy": false,
          "category": "WEATHER",
          "round": "single",
          "rowIndex": 0,
          "clueId": "g7735-s-c5-r0"
        },
        {
          "question": "A sailor's delight",
          "answer": "red sky at night",
          "value": 200,
          "dailyDouble": false,
          "tripleStumper": false,
          "isFinalJeopardy": false,
          "category": "WEATHER",
          "round": "single",
          "rowIndex": 1,
          "clueId": "g7735-s-c5-r1"
        },
        {
          "question": "What's called aurora australis in the southern sky is called this in the north",
          "answer": "the aurora borealis",
          "value": 300,
          "dailyDouble": false,
          "tripleStumper": false,
          "isFinalJeopardy": false,
          "category": "WEATHER",
          "round": "single",
          "rowIndex": 2,
          "clueId": "g7735-s-c5-r2"
        },
        {
          "question": "The largest measured 17 inches in circumference and weighed over a pound & a half",
          "answer": "a hailstone",
          "value": 400,
          "dailyDouble": false,
          "tripleStumper": false,
          "isFinalJeopardy": false,
          "category": "WEATHER",
          "round": "single",
          "rowIndex": 3,
          "clueId": "g7735-s-c5-r3"
        }
      ]
    },
    {
      "name": "POLITICAL SLOGANS",
      "round": "double",
      "position": 0,
      "clues": [
        {
          "question": "This preacher called his supporters \"The Rainbow Coalition\"",
          "answer": "Jesse Jackson",
          "value": 200,
          "dailyDouble": false,
          "tripleStumper": false,
          "isFinalJeopardy": false,
          "category": "POLITICAL SLOGANS",
          "round": "double",
          "rowIndex": 0,
          "clueId": "g7735-d-c0-r0"
        },
        {
          "question": "His post-WWI campaign promised \"back to normalcy\" but led to \"Teapot Dome\"",
          "answer": "Warren G. Harding",
          "value": 1000,
          "dailyDouble": false,
          "tripleStumper": false,
          "isFinalJeopardy": false,
          "category": "POLITICAL SLOGANS",
          "round": "double",
          "rowIndex": 1,
          "clueId": "g7735-d-c0-r1"
        }
      ]
    },
    {
      "name": "MATHEMATICS",
      "round": "double",
      "position": 1,
      "clues": [
        {
          "question": "XIV minus IX equals this",
          "answer": "5",
          "value": 200,
          "dailyDouble": false,
          "tripleStumper": false,
          "isFinalJeopardy": false,
          "category": "MATHEMATICS",
          "round": "double",
          "rowIndex": 0,
          "clueId": "g7735-d-c1-r0"
        },
        {
          "question": "Reason parents gave in the '60s for not helping their kids with their homework",
          "answer": "not being able to understand the new math",
          "value": 400,
          "dailyDouble": false,
          "tripleStumper": false,
          "isFinalJeopardy": false,
          "category": "MATHEMATICS",
          "round": "double",
          "rowIndex": 1,
          "clueId": "g7735-d-c1-r1"
        },
        {
          "question": "Branch named from the Latin word for pebble comes in \"differential\" & \"integral\"",
          "answer": "calculus",
          "value": 600,
          "dailyDouble": false,
          "tripleStumper": false,
          "isFinalJeopardy": false,
          "category": "MATHEMATICS",
          "round": "double",
          "rowIndex": 2,
          "clueId": "g7735-d-c1-r2"
        },
        {
          "question": "In \"chisenbop\", children are taught to calculate on these",
          "answer": "the fingers",
          "value": 800,
          "dailyDouble": false,
          "tripleStumper": false,
          "isFinalJeopardy": false,
          "category": "MATHEMATICS",
          "round": "double",
          "rowIndex": 3,
          "clueId": "g7735-d-c1-r3"
        },
        {
          "question": "The reciprocal of 1/25",
          "answer": "25",
          "value": 1000,
          "dailyDouble": false,
          "tripleStumper": false,
          "isFinalJeopardy": false,
          "category": "MATHEMATICS",
          "round": "double",
          "rowIndex": 4,
          "clueId": "g7735-d-c1-r4"
        }
      ]
    },
    {
      "name": "PROTEST SONGS",
      "round": "double",
      "position": 2,
      "clues": [
        {
          "question": "Peter, Paul & Mary popularized this botanical lament",
          "answer": "\"Where Have All The Flowers Gone?\"",
          "value": 200,
          "dailyDouble": false,
          "tripleStumper": false,
          "isFinalJeopardy": false,
          "category": "PROTEST SONGS",
          "round": "double",
          "rowIndex": 0,
          "clueId": "g7735-d-c2-r0"
        },
        {
          "question": "In John Lennon's song, it's \"all we are saying\"",
          "answer": "\"Give Peace A Chance\"",
          "value": 400,
          "dailyDouble": false,
          "tripleStumper": false,
          "isFinalJeopardy": false,
          "category": "PROTEST SONGS",
          "round": "double",
          "rowIndex": 1,
          "clueId": "g7735-d-c2-r1"
        },
        {
          "question": "\"Without him, Caesar would have stood alone\"",
          "answer": "the Universal Soldier",
          "value": 1000,
          "dailyDouble": false,
          "tripleStumper": true,
          "isFinalJeopardy": false,
          "category": "PROTEST SONGS",
          "round": "double",
          "rowIndex": 2,
          "clueId": "g7735-d-c2-r2"
        }
      ]
    },
    {
      "name": "\"TIME\"S",
      "round": "double",
      "position": 3,
      "clues": [
        {
          "question": "It's bounded by 7th, 42nd & Broadway",
          "answer": "Times Square",
          "value": 200,
          "dailyDouble": false,
          "tripleStumper": false,
          "isFinalJeopardy": false,
          "category": "\"TIME\"S",
          "round": "double",
          "rowIndex": 0,
          "clueId": "g7735-d-c3-r0"
        },
        {
          "question": "Jim Croce's unique storage technique",
          "answer": "time in a bottle",
          "value": 400,
          "dailyDouble": false,
          "tripleStumper": false,
          "isFinalJeopardy": false,
          "category": "\"TIME\"S",
          "round": "double",
          "rowIndex": 1,
          "clueId": "g7735-d-c3-r1"
        },
        {
          "question": "In the film \"Time After Time\", H.G. Wells himself uses this device from his 1895 novel",
          "answer": "the time machine",
          "value": 600,
          "dailyDouble": false,
          "tripleStumper": false,
          "isFinalJeopardy": false,
          "category": "\"TIME\"S",
          "round": "double",
          "rowIndex": 2,
          "clueId": "g7735-d-c3-r2"
        },
        {
          "question": "Phrase meaning \"at critical moment\", it's from the practice of marking time by notching wood",
          "answer": "in the nick of time",
          "value": 800,
          "dailyDouble": false,
          "tripleStumper": false,
          "isFinalJeopardy": false,
          "category": "\"TIME\"S",
          "round": "double",
          "rowIndex": 3,
          "clueId": "g7735-d-c3-r3"
        },
        {
          "question": "Ben Franklin's advice to young tradesmen",
          "answer": "time is money",
          "value": 1000,
          "dailyDouble": false,
          "tripleStumper": true,
          "isFinalJeopardy": false,
          "category": "\"TIME\"S",
          "round": "double",
          "rowIndex": 4,
          "clueId": "g7735-d-c3-r4"
        }
      ]
    },
    {
      "name": "CHINA",
      "round": "double",
      "position": 4,
      "clues": [
        {
          "question": "Mythological symbol of China, theirs never eats virgins or is slain by knights",
          "answer": "a dragon",
          "value": 200,
          "dailyDouble": false,
          "tripleStumper": false,
          "isFinalJeopardy": false,
          "category": "CHINA",
          "round": "double",
          "rowIndex": 0,
          "clueId": "g7735-d-c4-r0"
        },
        {
          "question": "In ancient times, only those of royal blood could own this dog",
          "answer": "a Pekingese",
          "value": 400,
          "dailyDouble": false,
          "tripleStumper": false,
          "isFinalJeopardy": false,
          "category": "CHINA",
          "round": "double",
          "rowIndex": 1,
          "clueId": "g7735-d-c4-r1"
        }
      ]
    },
    {
      "name": "ANIMALS",
      "round": "double",
      "position": 5,
      "clues": [
        {
          "question": "Its height gives it the greatest range of vision of any terrestrial animal",
          "answer": "a giraffe",
          "value": 200,
          "dailyDouble": false,
          "tripleStumper": false,
          "isFinalJeopardy": false,
          "category": "ANIMALS",
          "round": "double",
          "rowIndex": 0,
          "clueId": "g7735-d-c5-r0"
        },
        {
          "question": "Animal symbol for the '88 Olympics & Frosted Flakes",
          "answer": "the tiger",
          "value": 400,
          "dailyDouble": false,
          "tripleStumper": false,
          "isFinalJeopardy": false,
          "category": "ANIMALS",
          "round": "double",
          "rowIndex": 1,
          "clueId": "g7735-d-c5-r1"
        },
        {
          "question": "The order they belong to, Proboscidea, is named for their most distinguishing feature",
          "answer": "elephants",
          "value": 600,
          "dailyDouble": false,
          "tripleStumper": true,
          "isFinalJeopardy": false,
          "category": "ANIMALS",
          "round": "double",
          "rowIndex": 2,
          "clueId": "g7735-d-c5-r2"
        },
        {
          "question": "3-letter Australian bird of crossword puzzle fame, it's 2nd tallest in the world",
          "answer": "an emu",
          "value": 800,
          "dailyDouble": false,
          "tripleStumper": false,
          "isFinalJeopardy": false,
          "category": "ANIMALS",
          "round": "double",
          "rowIndex": 3,
          "clueId": "g7735-d-c5-r3"
        },
        {
          "question": "Its name comes from the Spanish el lagarto, meaning \"lizard\"",
          "answer": "an alligator",
          "value": 1000,
          "dailyDouble": true,
          "tripleStumper": false,
          "isFinalJeopardy": false,
          "category": "ANIMALS",
          "round": "double",
          "rowIndex": 4,
          "clueId": "g7735-d-c5-r4"
        }
      ]
    },
    {
      "name": "ASTRONOMY",
      "round": "final",
      "position": 0,
      "clues": [
        {
          "question": "After the Sun & the Moon, the brightest astronomical object regularly seen in our sky",
          "answer": "the planet Venus",
          "value": null,
          "dailyDouble": false,
          "tripleStumper": false,
          "isFinalJeopardy": true,
          "category": "ASTRONOMY",
          "round": "final",
          "rowIndex": 0,
          "clueId": "g7735-f-c0-r0"
        }
      ]
    }
  ]
}