{
  "gameId": 1042,
  "showNumber": 3307,
  "airDate": "January 12, 1999",
  "season": null,
  "isSpecial": false,
  "tournamentType": null,
  "categories": [
    {
      "name": "NO. 1 HITS",
      "round": "single",
      "position": 0,
      "clues": [
        {
          "question": "In 1986 she topped the charts with \"How Will I Know\" & \"The Greatest Love of All\"",
          "answer": "Whitney Houston",
          "value": 100,
          "dailyDouble": false,
          "tripleStumper": false,
          "isFinalJeopardy": false,
          "category": "NO. 1 HITS",
          "round": "single",
          "rowIndex": 0,
          "clueId": "g1042-s-c0-r0"
        },
        {
          "question": "1984s \"The Reflex\" was this band's first No. 1 song in the U.S.; \"Hungry Like The Wolf\" peaked at No. 3",
          "answer": "Duran Duran",
          "value": 200,
          "dailyDouble": false,
          "tripleStumper": false,
          "isFinalJeopardy": false,
          "category": "NO. 1 HITS",
          "round": "single",
          "rowIndex": 1,
          "clueId": "g1042-s-c0-r1"
        },
        {
          "question": "This singer was habit-forming with his 1986 hit \"Addicted To Love\"",
          "answer": "Robert Palmer",
          "value": 300,
          "dailyDouble": false,
          "tripleStumper": false,
          "isFinalJeopardy": false,
          "category": "NO. 1 HITS",
          "round": "single",
          "rowIndex": 2,
          "clueId": "g1042-s-c0-r2"
        },
        {
          "question": "The movie \"Buster\" starred this singer & drummer, who hit No. 1 with \"Two Hearts\", the movie's theme",
          "answer": "Phil Collins",
          "value": 400,
          "dailyDouble": false,
          "tripleStumper": false,
          "isFinalJeopardy": false,
          "category": "NO. 1 HITS",
          "round": "single",
          "rowIndex": 3,
          "clueId": "g1042-s-c0-r3"
        },
        {
          "question": "No. 1 songs from her \"Forever Your Girl\" album include the title track & \"Cold Hearted\"",
          "answer": "Paula Abdul",
          "value": 500,
          "dailyDouble": false,
          "tripleStumper": false,
          "isFinalJeopardy": false,
          "category": "NO. 1 HITS",
          "round": "single",
          "rowIndex": 4,
          "clueId": "g1042-s-c0-r4"
        }
      ]
    },
    {
      "name": "WWII",
      "round": "single",
      "position": 1,
      "clues": [
        {
          "question": "After the invasion of Poland, Great Britain & this nation declared war on Germany on September 3, 1939",
          "answer": "France",
          "value": 100,
          "dailyDouble": false,
          "tripleStumper": false,
          "isFinalJeopardy": false,
          "category": "WWII",
          "round": "single",
          "rowIndex": 0,
          "clueId": "g1042-s-c1-r0"
        },
        {
          "question": "Led by Anilewicz, the valiant fighters of this Polish city area held off Nazi attacks in 1943",
          "answer": "The Warsaw Ghetto",
          "value": 200,
          "dailyDouble": false,
          "tripleStumper": false,
          "isFinalJeopardy": false,
          "category": "WWII",
          "round": "single",
          "rowIndex": 1,
          "clueId": "g1042-s-c1-r1"
        },
        {
          "question": "Gen. McAuliffe's famous one-word reply to a German demand for surrender during the Battle of the Bulge",
          "answer": "\"Nuts!\"",
          "value": 300,
          "dailyDouble": false,
          "tripleStumper": false,
          "isFinalJeopardy": false,
          "category": "WWII",
          "round": "single",
          "rowIndex": 2,
          "clueId": "g1042-s-c1-r2"
        },
        {
          "question": "Seen here, he commanded the British 8th Army from 1942 to 1944",
          "answer": "Gen. Bernard Montgomery (of El-Alamein)",
          "value": 500,
          "dailyDouble": true,
          "tripleStumper": true,
          "isFinalJeopardy": false,
          "category": "WWII",
          "round": "single",
          "rowIndex": 3,
          "clueId": "g1042-s-c1-r3"
        },
        {
          "question": "This admiral directed Japan's naval operations in the year following Pearl Harbor",
          "answer": "Isoroku Yamamoto",
          "value": 500,
          "dailyDouble": false,
          "tripleStumper": true,
          "isFinalJeopardy": false,
          "category": "WWII",
          "round": "single",
          "rowIndex": 4,
          "clueId": "g1042-s-c1-r4"
        }
      ]
    },
    {
      "name": "THE 3 TENORS",
      "round": "single",
      "position": 2,
      "clues": [
        {
          "question": "The boys first teamed up in 1990 for a concert at the Baths of Caracalla in this city",
          "answer": "Rome",
          "value": 100,
          "dailyDouble": false,
          "tripleStumper": false,
          "isFinalJeopardy": false,
          "category": "THE 3 TENORS",
          "round": "single",
          "rowIndex": 0,
          "clueId": "g1042-s-c2-r0"
        },
        {
          "question": "The 3 Tenors inspired Kathleen Cassello, Kallen Esperian & Cynthia Lawrence to tour as this group",
          "answer": "The 3 Sopranos",
          "value": 200,
          "dailyDouble": false,
          "tripleStumper": false,
          "isFinalJeopardy": false,
          "category": "THE 3 TENORS",
          "round": "single",
          "rowIndex": 1,
          "clueId": "g1042-s-c2-r1"
        },
        {
          "question": "Among the classic songs interpreted by Pavarotti is this one also called \"Nel Blu, Dipinto Di Blu\"",
          "answer": "\"Volare\"",
          "value": 300,
          "dailyDouble": false,
          "tripleStumper": true,
          "isFinalJeopardy": false,
          "category": "THE 3 TENORS",
          "round": "single",
          "rowIndex": 2,
          "clueId": "g1042-s-c2-r2"
        },
        {
          "question": "On their 1994 & 1998 albums, Luciano performs \"Nessun Dorma\" from this composer's \"Turandot\"",
          "answer": "Giacomo Puccini",
          "value": 400,
          "dailyDouble": false,
          "tripleStumper": false,
          "isFinalJeopardy": false,
          "category": "THE 3 TENORS",
          "round": "single",
          "rowIndex": 3,
          "clueId": "g1042-s-c2-r3"
        },
        {
          "question": "From Greek for a certain musical instrument, it's the type of tenor Placido Domingo is",
          "answer": "Lyric",
          "value": 500,
          "dailyDouble": false,
          "tripleStumper": false,
          "isFinalJeopardy": false,
          "category": "THE 3 TENORS",
          "round": "single",
          "rowIndex": 4,
          "clueId": "g1042-s-c2-r4"
        }
      ]
    },
    {
      "name": "THE 4 SEASONS",
      "round": "single",
      "position": 3,
      "clues": [
        {
          "question": "Chamonix, France was the site of the first of these Olympics in 1924",
          "answer": "Winter Olympics",
          "value": 100,
          "dailyDouble": false,
          "tripleStumper": false,
          "isFinalJeopardy": false,
          "category": "THE 4 SEASONS",
          "round": "single",
          "rowIndex": 0,
          "clueId": "g1042-s-c3-r0"
        },
        {
          "question": "The first day of summer in Bolivia is in this month",
          "answer": "December",
          "value": 200,
          "dailyDouble": false,
          "tripleStumper": false,
          "isFinalJeopardy": false,
          "category": "THE 4 SEASONS",
          "round": "single",
          "rowIndex": 1,
          "clueId": "g1042-s-c3-r1"
        },
        {
          "question": "In Italy, spring is known as this; pass the pasta!",
          "answer": "Primavera",
          "value": 300,
          "dailyDouble": false,
          "tripleStumper": false,
          "isFinalJeopardy": false,
          "category": "THE 4 SEASONS",
          "round": "single",
          "rowIndex": 2,
          "clueId": "g1042-s-c3-r2"
        },
        {
          "question": "Thomas Paine scorned this seasonal warrior & the \"Sunshine Patriot\" in a 1776 pamphlet",
          "answer": "Summer soldier",
          "value": 400,
          "dailyDouble": false,
          "tripleStumper": false,
          "isFinalJeopardy": false,
          "category": "THE 4 SEASONS",
          "round": "single",
          "rowIndex": 3,
          "clueId": "g1042-s-c3-r3"
        },
        {
          "question": "In the first line of \"Richard III\", this is \"Made glorious summer by this sun of York\"",
          "answer": "\"The winter of our discontent\"",
          "value": 500,
          "dailyDouble": false,
          "tripleStumper": false,
          "isFinalJeopardy": false,
          "category": "THE 4 SEASONS",
          "round": "single",
          "rowIndex": 4,
          "clueId": "g1042-s-c3-r4"
        }
      ]
    },
    {
      "name": "THE 5 BOOKS OF MOSES",
      "round": "single",
      "position": 4,
      "clues": [
        {
          "question": "After losing his coat of many colors to his brothers, he lost another garment to Potiphar's eager wife",
          "answer": "Joseph",
          "value": 100,
          "dailyDouble": false,
          "tripleStumper": false,
          "isFinalJeopardy": false,
          "category": "THE 5 BOOKS OF MOSES",
          "round": "single",
          "rowIndex": 0,
          "clueId": "g1042-s-c4-r0"
        },
        {
          "question": "Name of the book whose second verse begins, \"Take ye the sum of all the congregation\"",
          "answer": "Numbers",
          "value": 300,
          "dailyDouble": false,
          "tripleStumper": false,
          "isFinalJeopardy": false,
          "category": "THE 5 BOOKS OF MOSES",
          "round": "single",
          "rowIndex": 1,
          "clueId": "g1042-s-c4-r1"
        },
        {
          "question": "This fifth book of the Pentateuch consists mostly of Moses laying down the law",
          "answer": "Deuteronomy",
          "value": 400,
          "dailyDouble": false,
          "tripleStumper": false,
          "isFinalJeopardy": false,
          "category": "THE 5 BOOKS OF MOSES",
          "round": "single",
          "rowIndex": 2,
          "clueId": "g1042-s-c4-r2"
        },
        {
          "question": "Sarah's handmaid bore Abraham this son & was told, \"His hand will be against every man\"",
          "answer": "Ishmael",
          "value": 500,
          "dailyDouble": false,
          "tripleStumper": false,
          "isFinalJeopardy": false,
          "category": "THE 5 BOOKS OF MOSES",
          "round": "single",
          "rowIndex": 3,
          "clueId": "g1042-s-c4-r3"
        }
      ]
    },
    {
      "name": "THE \"6\"th SENSE",
      "round": "single",
      "position": 5,
      "clues": [
        {
          "question": "In the old saw, it precedes \"Half a dozen of the other\"",
          "answer": "6 of 1",
          "value": 100,
          "dailyDouble": false,
          "tripleStumper": false,
          "isFinalJeopardy": false,
          "category": "THE \"6\"th SENSE",
          "round": "single",
          "rowIndex": 0,
          "clueId": "g1042-s-c5-r0"
        },
        {
          "question": "Tod Stiles & Buzz Murdock cruised America in a 1960 Corvette in this TV series",
          "answer": "Route 66",
          "value": 200,
          "dailyDouble": false,
          "tripleStumper": false,
          "isFinalJeopardy": false,
          "category": "THE \"6\"th SENSE",
          "round": "single",
          "rowIndex": 1,
          "clueId": "g1042-s-c5-r1"
        },
        {
          "question": "Ah, yes, I remember it well, this year of the original \"Woodstock Music & Art Fair\"",
          "answer": "1969",
          "value": 300,
          "dailyDouble": false,
          "tripleStumper": false,
          "isFinalJeopardy": false,
          "category": "THE \"6\"th SENSE",
          "round": "single",
          "rowIndex": 2,
          "clueId": "g1042-s-c5-r2"
        },
        {
          "question": "According to Tennyson, the number of men in the Light Brigade during its fateful charge",
          "answer": "The 600",
          "value": 400,
          "dailyDouble": false,
          "tripleStumper": false,
          "isFinalJeopardy": false,
          "category": "THE \"6\"th SENSE",
          "round": "single",
          "rowIndex": 3,
          "clueId": "g1042-s-c5-r3"
        },
        {
          "question": "In both an Iron Maiden hit song & the apocalypse of St. John, it's the number of the beast",
          "answer": "666",
          "value": 500,
          "dailyDouble": false,
          "tripleStumper": false,
          "isFinalJeopardy": false,
          "category": "THE \"6\"th SENSE",
          "round": "single",
          "rowIndex": 4,
          "clueId": "g1042-s-c5-r4"
        }
      ]
    },
    {
      "name": "METRO MIAMI",
      "round": "double",
      "position": 0,
      "clues": [
        {
          "question": "Warm, inviting Miami lies just 2 degrees north of this tropic line",
          "answer": "Tropic of Cancer",
          "value": 200,
          "dailyDouble": false,
          "tripleStumper": false,
          "isFinalJeopardy": false,
          "category": "METRO MIAMI",
          "round": "double",
          "rowIndex": 0,
          "clueId": "g1042-d-c0-r0"
        },
        {
          "question": "You may have to claw your way into Joe's popular spot for the \"stone\" type of these crustaceans",
          "answer": "Crabs",
          "value": 400,
          "dailyDouble": false,
          "tripleStumper": false,
          "isFinalJeopardy": false,
          "category": "METRO MIAMI",
          "round": "double",
          "rowIndex": 1,
          "clueId": "g1042-d-c0-r1"
        },
        {
          "question": "The University of Miami football team shares its name with these dreaded local events",
          "answer": "hurricanes",
          "value": 600,
          "dailyDouble": false,
          "tripleStumper": false,
          "isFinalJeopardy": false,
          "category": "METRO MIAMI",
          "round": "double",
          "rowIndex": 2,
          "clueId": "g1042-d-c0-r2"
        },
        {
          "question": "It's one of Miami Beach's best-known hotels & perhaps the one with the most elegant name",
          "answer": "The Fontainebleau",
          "value": 800,
          "dailyDouble": false,
          "tripleStumper": false,
          "isFinalJeopardy": false,
          "category": "METRO MIAMI",
          "round": "double",
          "rowIndex": 3,
          "clueId": "g1042-d-c0-r3"
        },
        {
          "question": "Directional name for the area that's the home of Miami's Art Deco District",
          "answer": "South Beach",
          "value": 1000,
          "dailyDouble": false,
          "tripleStumper": false,
          "isFinalJeopardy": false,
          "category": "METRO MIAMI",
          "round": "double",
          "rowIndex": 4,
          "clueId": "g1042-d-c0-r4"
        }
      ]
    },
    {
      "name": "BLACK & WHITE CLASSICS",
      "round": "double",
      "position": 1,
      "clues": [
        {
          "question": "Stuck in the wilderness in \"The Gold Rush\", he boils his boot for dinner",
          "answer": "Charlie Chaplin",
          "value": 200,
          "dailyDouble": false,
          "tripleStumper": false,
          "isFinalJeopardy": false,
          "category": "BLACK & WHITE CLASSICS",
          "round": "double",
          "rowIndex": 0,
          "clueId": "g1042-d-c1-r0"
        },
        {
          "question": "In a 1944 classic, it's the title type of insurance Barbara Stanwyck takes out on her husband",
          "answer": "Double Indemnity",
          "value": 400,
          "dailyDouble": false,
          "tripleStumper": false,
          "isFinalJeopardy": false,
          "category": "BLACK & WHITE CLASSICS",
          "round": "double",
          "rowIndex": 1,
          "clueId": "g1042-d-c1-r1"
        },
        {
          "question": "(Hi, I'm Janet Leigh.)  In \"Psycho\", it's the name of the establishment where I met my end",
          "answer": "the Bates Motel",
          "value": 1100,
          "dailyDouble": true,
          "tripleStumper": false,
          "isFinalJeopardy": false,
          "category": "BLACK & WHITE CLASSICS",
          "round": "double",
          "rowIndex": 2,
          "clueId": "g1042-d-c1-r2"
        },
        {
          "question": "In 1953 Audrey Hepburn won hearts as the runaway princess in this film",
          "answer": "Roman Holiday",
          "value": 800,
          "dailyDouble": false,
          "tripleStumper": false,
          "isFinalJeopardy": false,
          "category": "BLACK & WHITE CLASSICS",
          "round": "double",
          "rowIndex": 3,
          "clueId": "g1042-d-c1-r3"
        },
        {
          "question": "This 1939 film includes the line \"What do they know of heaven and hell, Cathy, who know nothing of life?\"",
          "answer": "Wuthering Heights",
          "value": 1000,
          "dailyDouble": false,
          "tripleStumper": false,
          "isFinalJeopardy": false,
          "category": "BLACK & WHITE CLASSICS",
          "round": "double",
          "rowIndex": 4,
          "clueId": "g1042-d-c1-r4"
        }
      ]
    },
    {
      "name": "SPELL IT OUT",
      "round": "double",
      "position": 2,
      "clues": [
        {
          "question": "A sexy 60-year-old would know how to spell...",
          "answer": "S-E-X-A-G-E-N-A-R-I-A-N",
          "value": 200,
          "dailyDouble": false,
          "tripleStumper": false,
          "isFinalJeopardy": false,
          "category": "SPELL IT OUT",
          "round": "double",
          "rowIndex": 0,
          "clueId": "g1042-d-c2-r0"
        },
        {
          "question": "Phone home & then spell...",
          "answer": "E-X-T-R-A-T-E-R-R-E-S-T-R-I-A-L",
          "value": 600,
          "dailyDouble": false,
          "tripleStumper": false,
          "isFinalJeopardy": false,
          "category": "SPELL IT OUT",
          "round": "double",
          "rowIndex": 1,
          "clueId": "g1042-d-c2-r1"
        }
      ]
    },
    {
      "name": "COMMUNICATION",
      "round": "double",
      "position": 3,
      "clues": [
        {
          "question": "In 1979 Saatchi & Saatchi, Britain's largest of these agencies, helped bring Margaret Thatcher to power",
          "answer": "Advertising",
          "value": 200,
          "dailyDouble": false,
          "tripleStumper": true,
          "isFinalJeopardy": false,
          "category": "COMMUNICATION",
          "round": "double",
          "rowIndex": 0,
          "clueId": "g1042-d-c3-r0"
        },
        {
          "question": "One channel of communication, perhaps with the dead; its plural form means all press & broadcasters",
          "answer": "a medium",
          "value": 400,
          "dailyDouble": false,
          "tripleStumper": false,
          "isFinalJeopardy": false,
          "category": "COMMUNICATION",
          "round": "double",
          "rowIndex": 1,
          "clueId": "g1042-d-c3-r1"
        },
        {
          "question": "Violin strings do it to produce sound; a pager does it to signal you silently",
          "answer": "Vibrate",
          "value": 600,
          "dailyDouble": false,
          "tripleStumper": false,
          "isFinalJeopardy": false,
          "category": "COMMUNICATION",
          "round": "double",
          "rowIndex": 2,
          "clueId": "g1042-d-c3-r2"
        },
        {
          "question": "A classic model of communication refers to the person at the end stage as this, like part of a phone",
          "answer": "Receiver",
          "value": 800,
          "dailyDouble": false,
          "tripleStumper": false,
          "isFinalJeopardy": false,
          "category": "COMMUNICATION",
          "round": "double",
          "rowIndex": 3,
          "clueId": "g1042-d-c3-r3"
        },
        {
          "question": "Add 3 letters to \"oration\" to get this word for the conclusion of a speech",
          "answer": "Per (Peroration)",
          "value": 1000,
          "dailyDouble": false,
          "tripleStumper": true,
          "isFinalJeopardy": false,
          "category": "COMMUNICATION",
          "round": "double",
          "rowIndex": 4,
          "clueId": "g1042-d-c3-r4"
        }
      ]
    },
    {
      "name": "RICH FELLAS",
      "round": "double",
      "position": 4,
      "clues": [
        {
          "question": "The villainous broadcast tycoon in \"Tomorrow Never Dies\" reminded some of this Australian-born mogul",
          "answer": "Rupert Murdoch",
          "value": 200,
          "dailyDouble": false,
          "tripleStumper": false,
          "isFinalJeopardy": false,
          "category": "RICH FELLAS",
          "round": "double",
          "rowIndex": 0,
          "clueId": "g1042-d-c4-r0"
        },
        {
          "question": "The 2 millionaires Jacqueline Bouvier married",
          "answer": "John F. Kennedy & Aristotle Onassis",
          "value": 400,
          "dailyDouble": false,
          "tripleStumper": false,
          "isFinalJeopardy": false,
          "category": "RICH FELLAS",
          "round": "double",
          "rowIndex": 1,
          "clueId": "g1042-d-c4-r1"
        },
        {
          "question": "Pulitzer winner James Merrill could focus on poetry -- his dad founded a brokerage house with this man",
          "answer": "Edmund Lynch",
          "value": 600,
          "dailyDouble": false,
          "tripleStumper": false,
          "isFinalJeopardy": false,
          "category": "RICH FELLAS",
          "round": "double",
          "rowIndex": 2,
          "clueId": "g1042-d-c4-r2"
        },
        {
          "question": "This fast food co.'s stock took a quarter pounding when it didn't make the list of Warren Buffett's major holdings",
          "answer": "McDonald's",
          "value": 800,
          "dailyDouble": false,
          "tripleStumper": false,
          "isFinalJeopardy": false,
          "category": "RICH FELLAS",
          "round": "double",
          "rowIndex": 3,
          "clueId": "g1042-d-c4-r3"
        },
        {
          "question": "Once chairman of the Chase Manahattan Bank, he's a founding board member of the Trilateral Commission",
          "answer": "David Rockefeller",
          "value": 1000,
          "dailyDouble": false,
          "tripleStumper": true,
          "isFinalJeopardy": false,
          "category": "RICH FELLAS",
          "round": "double",
          "rowIndex": 4,
          "clueId": "g1042-d-c4-r4"
        }
      ]
    },
    {
      "name": "IT'S A MYSTERY",
      "round": "double",
      "position": 5,
      "clues": [
        {
          "question": "With his first Maigret novel in 1931, he's considered one of the inventors of the police procedural",
          "answer": "Georges Simenon",
          "value": 200,
          "dailyDouble": false,
          "tripleStumper": true,
          "isFinalJeopardy": false,
          "category": "IT'S A MYSTERY",
          "round": "double",
          "rowIndex": 0,
          "clueId": "g1042-d-c5-r0"
        },
        {
          "question": "Store det. Wolf J. Flywheel in the film \"The Big Store\", Ron Goulart made him a master detective in a 1998 book",
          "answer": "Groucho Marx",
          "value": 400,
          "dailyDouble": false,
          "tripleStumper": true,
          "isFinalJeopardy": false,
          "category": "IT'S A MYSTERY",
          "round": "double",
          "rowIndex": 1,
          "clueId": "g1042-d-c5-r1"
        },
        {
          "question": "His crime novel \"Rum Punch\" was filmed by Quentin Tarantino as \"Jackie Brown\"",
          "answer": "Elmore Leonard",
          "value": 600,
          "dailyDouble": false,
          "tripleStumper": false,
          "isFinalJeopardy": false,
          "category": "IT'S A MYSTERY",
          "round": "double",
          "rowIndex": 2,
          "clueId": "g1042-d-c5-r2"
        },
        {
          "question": "Mr. Contreras lives downstairs from this Paretsky P.I.",
          "answer": "VI Warshawski",
          "value": 800,
          "dailyDouble": false,
          "tripleStumper": false,
          "isFinalJeopardy": false,
          "category": "IT'S A MYSTERY",
          "round": "double",
          "rowIndex": 3,
          "clueId": "g1042-d-c5-r3"
        },
        {
          "question": "This \"L.A. Confidential\" author's \"My Dark Places\" looks into the real investigation of his mom's murder",
          "answer": "James Ellroy",
          "value": 1000,
          "dailyDouble": false,
          "tripleStumper": true,
          "isFinalJeopardy": false,
          "category": "IT'S A MYSTERY",
          "round": "double",
          "rowIndex": 4,
          "clueId": "g1042-d-c5-r4"
        }
      ]
    },
    {
      "name": "U.S. GOVERNMENT",
      "round": "final",
      "position": 0,
      "clues": [
        {
          "question": "In its history this government body has had a total of 108 members, 106 of them men",
          "answer": "The Supreme Court",
          "value": null,
          "dailyDouble": false,
          "tripleStumper": false,
          "isFinalJeopardy": true,
          "category": "U.S. GOVERNMENT",
          "round": "final",
          "rowIndex": 0,
          "clueId": "g1042-f-c0-r0"
        }
      ]
    }
  ]
}